wayback_machine_saver/__init__.py
wayback_machine_saver/__main__.py
wayback_machine_saver/config.py
wayback_machine_saver/wayback_machine_saver.py
wayback_machine_saver-0.3.1.dist-info/entry_points.txt
wayback_machine_saver-0.3.1.dist-info/LICENSE
wayback_machine_saver-0.3.1.dist-info/WHEEL
wayback_machine_saver-0.3.1.dist-info/METADATA
wayback_machine_saver-0.3.1.dist-info/RECORD
