Metadata-Version: 2.1
Name: wayback-machine-saver
Version: 0.3.1
Summary: Python tool for archiving web pages through Internet Archive Wayback Machine 
Home-page: https://github.com/Lee-W/wayback-machine-saver
License: MIT
Author: Wei Lee
Author-email: weilee.rx@gmail.com
Requires-Python: >=3.8,<4.0
Classifier: License :: OSI Approved :: MIT License
Classifier: Programming Language :: Python :: 3
Classifier: Programming Language :: Python :: 3.8
Classifier: Programming Language :: Python :: 3.9
Requires-Dist: click (>=7.1.2,<8.0.0)
Requires-Dist: httpx (>=0.18.0,<0.19.0)
Requires-Dist: tqdm (>=4.60.0,<5.0.0)
Project-URL: Repository, https://github.com/Lee-W/wayback-machine-saver
